src/config.py
src/main.py
src/htcondor/__init__.py
src/htcondor/htcondor.py
src/htcondor/types.py
src/ssh/cluster.py
src/styles/cluster_tool.tcss
src/widgets/__init__.py
src/widgets/cancel_confirm.py
src/widgets/condor_job_list.py
src/widgets/file_tail_viewer.py
src/widgets/job_file_viewer.py
src/widgets/sidebar.py
mpi_cluster_tools-0.2.9.dist-info/METADATA
mpi_cluster_tools-0.2.9.dist-info/WHEEL
mpi_cluster_tools-0.2.9.dist-info/entry_points.txt
mpi_cluster_tools-0.2.9.dist-info/RECORD
