Metadata-Version: 2.4
Name: mpi-cluster-tools
Version: 0.2.9
Summary: A collection of tools for monitoring and managing jobs on the mpi cluster.
Author-email: Benedict Armstrong <benedict.armstrong@inf.ethz.ch>
Requires-Python: >=3.12
Requires-Dist: paramiko>=3.5.1
Requires-Dist: textual-dev>=1.7.0
Requires-Dist: textual>=5.0.1
Requires-Dist: typer>=0.16.0
